{
 "Files" : [
  {
   "Path" : "C:/git/TRS-IO-M3/src/fpga/m3/v2.0/TRS-IO/src/filter.v",
   "Type" : "verilog"
  },
  {
   "Path" : "C:/git/TRS-IO-M3/src/fpga/m3/v2.0/TRS-IO/src/gowin_clkdiv/gowin_clkdiv0.v",
   "Type" : "verilog"
  },
  {
   "Path" : "C:/git/TRS-IO-M3/src/fpga/m3/v2.0/TRS-IO/src/gowin_clkdiv/gowin_clkdiv1.v",
   "Type" : "verilog"
  },
  {
   "Path" : "C:/git/TRS-IO-M3/src/fpga/m3/v2.0/TRS-IO/src/gowin_dpb/blk_mem_gen_2.v",
   "Type" : "verilog"
  },
  {
   "Path" : "C:/git/TRS-IO-M3/src/fpga/m3/v2.0/TRS-IO/src/gowin_dpb/blk_mem_gen_4.v",
   "Type" : "verilog"
  },
  {
   "Path" : "C:/git/TRS-IO-M3/src/fpga/m3/v2.0/TRS-IO/src/gowin_dpb/gowin_dpb0.v",
   "Type" : "verilog"
  },
  {
   "Path" : "C:/git/TRS-IO-M3/src/fpga/m3/v2.0/TRS-IO/src/gowin_dpb/gowin_dpb1.v",
   "Type" : "verilog"
  },
  {
   "Path" : "C:/git/TRS-IO-M3/src/fpga/m3/v2.0/TRS-IO/src/gowin_prom/blk_mem_gen_3.v",
   "Type" : "verilog"
  },
  {
   "Path" : "C:/git/TRS-IO-M3/src/fpga/m3/v2.0/TRS-IO/src/gowin_rpll/gowin_rpll.v",
   "Type" : "verilog"
  },
  {
   "Path" : "C:/git/TRS-IO-M3/src/fpga/m3/v2.0/TRS-IO/src/gowin_rpll/gowin_rpll0.v",
   "Type" : "verilog"
  },
  {
   "Path" : "C:/git/TRS-IO-M3/src/fpga/m3/v2.0/TRS-IO/src/main.v",
   "Type" : "verilog"
  },
  {
   "Path" : "C:/git/TRS-IO-M3/src/fpga/m3/v2.0/TRS-IO/src/trigger.v",
   "Type" : "verilog"
  }
 ],
 "IncludePath" : [

 ],
 "LoopLimit" : 2000,
 "ResultFile" : "C:/git/TRS-IO-M3/src/fpga/m3/v2.0/TRS-IO/impl/temp/rtl_parser.result",
 "Top" : "main",
 "VerilogStd" : "sysv",
 "VhdlStd" : "vhdl_93"
}